appdb.sqlite
lowbudget2gocli.py
lowbudget2_gocli-0.1.0.dist-info/entry_points.txt
lowbudget2_gocli-0.1.0.dist-info/WHEEL
lowbudget2_gocli-0.1.0.dist-info/METADATA
lowbudget2_gocli-0.1.0.dist-info/RECORD
