Metadata-Version: 2.1
Name: lowbudget2-gocli
Version: 0.1.0
Summary: A command line application that allows developers post, read, comment and like gossips
Author: Adeayo
Requires-Python: >=3.7,<4.0
Classifier: Programming Language :: Python :: 3
Classifier: Programming Language :: Python :: 3.7
Classifier: Programming Language :: Python :: 3.8
